{"stats":{"minecraft:killed_by":{"minecraft:player":9},"minecraft:custom":{"minecraft:interact_with_anvil":5,"minecraft:mob_kills":10,"minecraft:play_record":15,"minecraft:open_shulker_box":1,"minecraft:leave_game":50,"minecraft:time_since_death":59780,"minecraft:climb_one_cm":28033,"minecraft:time_since_rest":59809,"minecraft:sprint_one_cm":2988649,"minecraft:damage_taken":5994,"minecraft:walk_one_cm":1309115,"minecraft:drop":1037,"minecraft:damage_dealt":3842,"minecraft:fly_one_cm":14778420,"minecraft:player_kills":2,"minecraft:crouch_one_cm":93954,"minecraft:play_time":2533060,"minecraft:deaths":24,"minecraft:sneak_time":70989,"minecraft:jump":29281,"minecraft:total_world_time":3374798,"minecraft:fall_one_cm":19896},"minecraft:picked_up":{"minecraft:cracked_deepslate_tiles":1,"minecraft:clock":9,"minecraft:anvil":1,"minecraft:birch_button":1,"minecraft:acacia_button":9,"minecraft:light":2,"minecraft:golden_sword":1,"minecraft:music_disc_cat":3,"minecraft:white_stained_glass":1,"minecraft:blue_stained_glass_pane":10,"minecraft:oak_sign":6,"minecraft:glass_pane":1,"minecraft:red_sand":1,"minecraft:comparator":2,"minecraft:music_disc_far":3,"minecraft:netherite_axe":2,"minecraft:player_head":1667,"minecraft:music_disc_chirp":1,"minecraft:stick":1,"minecraft:music_disc_13":4,"minecraft:torch":1,"minecraft:music_disc_mellohi":1,"minecraft:gravel":1,"minecraft:sand":1,"minecraft:stone_button":3,"minecraft:diorite":1,"minecraft:redstone":5,"minecraft:music_disc_mall":4,"minecraft:command_block":2,"minecraft:diamond":3,"minecraft:polished_diorite":1,"minecraft:light_blue_stained_glass_pane":79,"minecraft:lever":1,"minecraft:polished_blackstone":1},"minecraft:killed":{"minecraft:axolotl":9,"minecraft:villager":1},"minecraft:used":{"minecraft:music_disc_far":3,"minecraft:diorite":297,"minecraft:flint_and_steel":8,"minecraft:smooth_quartz_slab":100,"minecraft:armor_stand":22,"minecraft:polished_blackstone":520,"minecraft:polished_andesite":3,"minecraft:oak_sign":6,"minecraft:axolotl_spawn_egg":12,"minecraft:chest":1,"minecraft:tinted_glass":4,"minecraft:stone":2,"minecraft:redstone_block":24,"minecraft:spruce_sign":1,"minecraft:white_dye":2,"minecraft:glow_ink_sac":2,"minecraft:player_head":2,"minecraft:waxed_copper_block":2,"minecraft:smooth_quartz_stairs":72,"minecraft:white_wool":146,"minecraft:torch":4,"minecraft:dirt":2,"minecraft:music_disc_cat":3,"minecraft:anvil":4,"minecraft:comparator":9,"minecraft:vine":2,"minecraft:tnt":8,"minecraft:birch_sign":5,"minecraft:cracked_deepslate_tiles":197,"minecraft:shulker_box":3,"minecraft:music_disc_13":3,"minecraft:polished_diorite":484,"minecraft:deepslate_tiles":7,"minecraft:music_disc_mellohi":1,"minecraft:glass":2,"minecraft:lever":25,"minecraft:light":397,"minecraft:black_concrete":18,"minecraft:bookshelf":2,"minecraft:quartz_pillar":19,"minecraft:command_block":61,"minecraft:quartz_slab":2,"minecraft:music_disc_mall":4,"minecraft:grass_block":74,"minecraft:barrier":421,"minecraft:stone_button":18,"minecraft:netherite_axe":14,"minecraft:music_disc_chirp":1,"minecraft:smooth_quartz":383,"minecraft:bedrock":2,"minecraft:birch_button":18,"minecraft:repeater":4,"minecraft:cobblestone":153,"minecraft:white_stained_glass":33,"minecraft:gold_block":13,"minecraft:repeating_command_block":8,"minecraft:smooth_stone_slab":2,"minecraft:stone_pressure_plate":3,"minecraft:jukebox":8,"minecraft:smooth_stone":58,"minecraft:cobbled_deepslate_wall":1},"minecraft:dropped":{"minecraft:blue_stained_glass_pane":133,"minecraft:anvil":1,"minecraft:clock":11,"minecraft:player_head":155,"minecraft:diamond":2,"minecraft:command_block":67,"minecraft:grass_block":1,"minecraft:glass_pane":2,"minecraft:acacia_button":9,"minecraft:stick":23,"minecraft:music_disc_13":1,"minecraft:stone_button":1,"minecraft:netherite_block":128,"minecraft:barrel":1,"minecraft:light_blue_stained_glass_pane":862,"minecraft:green_stained_glass_pane":1,"minecraft:white_stained_glass":1}},"DataVersion":3120}